jqqb/__init__.py
jqqb/operators.py
jqqb/rule.py
jqqb/rule_group.py
jqqb/utils.py
jqqb-1.5.0.dist-info/LICENSE
jqqb-1.5.0.dist-info/METADATA
jqqb-1.5.0.dist-info/WHEEL
jqqb-1.5.0.dist-info/top_level.txt
jqqb-1.5.0.dist-info/RECORD
