Metadata-Version: 2.1
Name: jqqb
Version: 1.5.0
Summary: Python parsing, evaluation and inspection tools for jQuery-QueryBuilder rules
Home-page: https://github.com/Connecting-Food/jQueryQueryBuilder
Author: Connecting Food
Author-email: developers@connecting-food.com
Classifier: Programming Language :: Python :: 3
Classifier: License :: OSI Approved :: MIT License
Classifier: Operating System :: OS Independent
Requires-Python: >=3.6
License-File: LICENSE
Requires-Dist: pytimeparse ~=1.1.8
